odoo/addons/l10n_hr_nkd/README.rst
odoo/addons/l10n_hr_nkd/__init__.py
odoo/addons/l10n_hr_nkd/__manifest__.py
odoo/addons/l10n_hr_nkd/data/l10n.hr.nkd.csv
odoo/addons/l10n_hr_nkd/i18n/hr.po
odoo/addons/l10n_hr_nkd/i18n/l10n_hr_nkd.pot
odoo/addons/l10n_hr_nkd/models/__init__.py
odoo/addons/l10n_hr_nkd/models/l10n_hr_nkd.py
odoo/addons/l10n_hr_nkd/models/res_company.py
odoo/addons/l10n_hr_nkd/models/res_partner.py
odoo/addons/l10n_hr_nkd/security/ir.model.access.csv
odoo/addons/l10n_hr_nkd/static/description/icon.png
odoo/addons/l10n_hr_nkd/views/l10n_hr_nkd_view.xml
odoo/addons/l10n_hr_nkd/views/res_company_view.xml
odoo/addons/l10n_hr_nkd/views/res_partner_view.xml
odoo_addon_l10n_hr_nkd-16.0.1.0.1.dist-info/METADATA
odoo_addon_l10n_hr_nkd-16.0.1.0.1.dist-info/WHEEL
odoo_addon_l10n_hr_nkd-16.0.1.0.1.dist-info/top_level.txt
odoo_addon_l10n_hr_nkd-16.0.1.0.1.dist-info/RECORD
